ghost.py
ghost_in_the_machine-0.0.75.dist-info/entry_points.txt
ghost_in_the_machine-0.0.75.dist-info/LICENSE
ghost_in_the_machine-0.0.75.dist-info/WHEEL
ghost_in_the_machine-0.0.75.dist-info/METADATA
ghost_in_the_machine-0.0.75.dist-info/RECORD
