Metadata-Version: 2.1
Name: ghost-in-the-machine
Version: 0.0.75
Summary: Manage your digital presence
License: CC0-1.0
Author: Angelo Gladding
Author-email: angelo@lahacker.net
Requires-Python: >=3.9,<4.0
Classifier: License :: CC0 1.0 Universal (CC0 1.0) Public Domain Dedication
Classifier: Programming Language :: Python :: 3
Classifier: Programming Language :: Python :: 3.9
Requires-Dist: understory (>=0.0.42,<0.0.43)
Project-URL: Homepage, https://angelogladding.com/code/ghost
